dorapy/__init__.py
dorapy/nn/__init__.py
dorapy/nn/initializer.py
dorapy/nn/layer.py
dorapy/nn/loss.py
dorapy/nn/model.py
dorapy/nn/net.py
dorapy/nn/optimizer.py
dorapy/utils/__init__.py
dorapy/utils/circle.py
dorapy/utils/data_iterator.py
dorapy/utils/dataset.py
dorapy/utils/dateTool.py
dorapy/utils/dirTool.py
dorapy/utils/downloader.py
dorapy/utils/exlTool.py
dorapy/utils/imgTool.py
dorapy/utils/listTool.py
dorapy/utils/math.py
dorapy/utils/mathTool.py
dorapy/utils/metric.py
dorapy/utils/seeder.py
dorapy/utils/spiderTool.py
dorapy/utils/structured_param.py
dorapy/utils/txtTool.py
dorapy/utils/videoTool.py
DoraPy-1.1.0.dist-info/LICENSE
DoraPy-1.1.0.dist-info/METADATA
DoraPy-1.1.0.dist-info/WHEEL
DoraPy-1.1.0.dist-info/top_level.txt
DoraPy-1.1.0.dist-info/RECORD
