Metadata-Version: 2.1
Name: DoraPy
Version: 1.1.0
Summary: Dorapy is a deep learning framework that focuses on data preprocessing.🛸
Home-page: https://github.com/CPG123456/DoraPy
Author: pgCai
Author-email: pgcai@tju.edu.cn
License: UNKNOWN
Project-URL: Bug Tracker, https://github.com/CPG123456/DoraPy/issues
Platform: UNKNOWN
Classifier: Programming Language :: Python :: 3
Classifier: License :: OSI Approved :: MIT License
Classifier: Operating System :: OS Independent
Requires-Python: >=3.6
License-File: LICENSE
